torch_custom_datasets-0.0.3.dist-info/licenses/LICENSE
torchdatasets/__init__.py
torchdatasets/vision/__init__.py
torchdatasets/vision/classification/__init__.py
torchdatasets/vision/classification/from_singledir.py
torchdatasets/vision/classification/from_subdirs.py
torchdatasets/vision/segmentation/__init__.py
torch_custom_datasets-0.0.3.dist-info/METADATA
torch_custom_datasets-0.0.3.dist-info/WHEEL
torch_custom_datasets-0.0.3.dist-info/top_level.txt
torch_custom_datasets-0.0.3.dist-info/RECORD
