Metadata-Version: 2.4
Name: torch-custom-datasets
Version: 0.0.3
Summary: A suite of custom PyTorch dataset loaders for vision tasks like classification and segmentation.
Author-email: Shubh Goyal <goyal.shubh0711@gmail.com>
License: Apache-2.0
Project-URL: Homepage, https://github.com/Shubh-Goyal-07/torch-datasets
Project-URL: Documentation, https://github.com/Shubh-Goyal-07/torch-datasets#readme
Project-URL: Source, https://github.com/Shubh-Goyal-07/torch-datasets
Project-URL: Tracker, https://github.com/Shubh-Goyal-07/torch-datasets/issues
Keywords: pytorch,datasets,torch,deep-learning,vision,classification,segmentation
Classifier: Development Status :: 3 - Alpha
Classifier: Intended Audience :: Developers
Classifier: Intended Audience :: Science/Research
Classifier: License :: OSI Approved :: Apache Software License
Classifier: Programming Language :: Python :: 3.9
Classifier: Programming Language :: Python :: 3.10
Classifier: Programming Language :: Python :: 3.11
Classifier: Topic :: Scientific/Engineering :: Artificial Intelligence
Requires-Python: <3.12,>=3.9
License-File: LICENSE
Requires-Dist: torch>=2.0.0
Requires-Dist: torchvision>=0.15.0
Requires-Dist: Pillow>=9.0.0
Requires-Dist: numpy>=1.22.0
Dynamic: license-file
